DocStringGenerator/AnthropicCommunicator.py
DocStringGenerator/BaseBotCommunicator.py
DocStringGenerator/CodeProcessor.py
DocStringGenerator/CommunicatorManager.py
DocStringGenerator/ConfigManager.py
DocStringGenerator/DependencyContainer copy.py
DocStringGenerator/DependencyContainer.py
DocStringGenerator/DocstringProcessor.py
DocStringGenerator/EmptyCommunicator.py
DocStringGenerator/FileCommunicator.py
DocStringGenerator/GoogleCommunicator.py
DocStringGenerator/OpenAICommunicator.py
DocStringGenerator/ResultThread.py
DocStringGenerator/Spinner.py
DocStringGenerator/Utility.py
DocStringGenerator/__init__.py
AIDocStringGenerator-1.0.dist-info/LICENCE
AIDocStringGenerator-1.0.dist-info/METADATA
AIDocStringGenerator-1.0.dist-info/WHEEL
AIDocStringGenerator-1.0.dist-info/entry_points.txt
AIDocStringGenerator-1.0.dist-info/top_level.txt
AIDocStringGenerator-1.0.dist-info/RECORD
