Metadata-Version: 2.1
Name: AIDocStringGenerator
Version: 1.0
Summary: AIDocStringGenerator is an automated tool that utilizes AI technologies like Anthropic and OpenAI GPT-3.5 to generate and manage docstrings in Python code. It streamlines documentation by processing both single files and entire directories, offering customizable settings for docstring verbosity and style. This tool is ideal for enhancing code readability and maintainability in Python projects.
Home-page: https://github.com/fantasiiio/AIDocStringGenerator
Author: Francois Girard
Author-email: fantasiiio@hotmail.com
License-File: LICENCE
Requires-Dist: AIDocStringGenerator
Requires-Dist: annotated-types ==0.6.0
Requires-Dist: anyio ==4.2.0
Requires-Dist: cachetools ==5.3.2
Requires-Dist: certifi ==2023.11.17
Requires-Dist: charset-normalizer ==3.3.2
Requires-Dist: colorama ==0.4.6
Requires-Dist: distro ==1.9.0
Requires-Dist: exceptiongroup ==1.2.0
Requires-Dist: google-ai-generativelanguage ==0.4.0
Requires-Dist: google-api-core ==2.15.0
Requires-Dist: google-auth ==2.25.2
Requires-Dist: google-generativeai ==0.3.2
Requires-Dist: googleapis-common-protos ==1.62.0
Requires-Dist: grpcio ==1.60.0
Requires-Dist: grpcio-status ==1.60.0
Requires-Dist: h11 ==0.14.0
Requires-Dist: httpcore ==1.0.2
Requires-Dist: httpx ==0.26.0
Requires-Dist: idna ==3.6
Requires-Dist: iniconfig ==2.0.0
Requires-Dist: openai ==1.6.1
Requires-Dist: packaging ==23.2
Requires-Dist: pluggy ==1.3.0
Requires-Dist: proto-plus ==1.23.0
Requires-Dist: protobuf ==4.25.1
Requires-Dist: pyasn1 ==0.5.1
Requires-Dist: pyasn1-modules ==0.3.0
Requires-Dist: pydantic ==2.5.3
Requires-Dist: pydantic-core ==2.14.6
Requires-Dist: pytest ==7.4.4
Requires-Dist: python-dotenv ==1.0.0
Requires-Dist: requests ==2.31.0
Requires-Dist: rsa ==4.9
Requires-Dist: sniffio ==1.3.0
Requires-Dist: tomli ==2.0.1
Requires-Dist: tqdm ==4.66.1
Requires-Dist: typing-extensions ==4.9.0
Requires-Dist: urllib3 ==2.1.0
